chemise/__init__.py
chemise/misc.py
chemise/test_utils.py
chemise/utils.py
chemise-0.0.1a1.dist-info/METADATA
chemise-0.0.1a1.dist-info/WHEEL
chemise-0.0.1a1.dist-info/top_level.txt
chemise-0.0.1a1.dist-info/RECORD
