Metadata-Version: 2.1
Name: chemise
Version: 0.0.1a1
Summary: Wrapper for training flax models
Home-page: https://github.com/timcargan/chemise
Author: Tim Cargan
Platform: unix
Platform: linux
Platform: osx
Classifier: Programming Language :: Python :: 3
Classifier: Programming Language :: Python :: 3 :: Only
Classifier: Programming Language :: Python :: 3.9
Classifier: Programming Language :: Python :: 3.10
Requires-Python: >=3.9
Requires-Dist: absl-py
Requires-Dist: numpy
Requires-Dist: jax
Requires-Dist: jaxtyping
Requires-Dist: einops
Requires-Dist: flax
Requires-Dist: orbax
Requires-Dist: chex
Requires-Dist: setuptools
Requires-Dist: plotext
Requires-Dist: rich (>=12.4)
